inspire_dojson/__init__.py
inspire_dojson/api.py
inspire_dojson/errors.py
inspire_dojson/model.py
inspire_dojson/cds/__init__.py
inspire_dojson/cds/model.py
inspire_dojson/cds/rules.py
inspire_dojson/common/__init__.py
inspire_dojson/common/rules.py
inspire_dojson/conferences/__init__.py
inspire_dojson/conferences/model.py
inspire_dojson/conferences/rules.py
inspire_dojson/data/__init__.py
inspire_dojson/data/model.py
inspire_dojson/data/rules.py
inspire_dojson/experiments/__init__.py
inspire_dojson/experiments/model.py
inspire_dojson/experiments/rules.py
inspire_dojson/hep/__init__.py
inspire_dojson/hep/model.py
inspire_dojson/hep/rules/__init__.py
inspire_dojson/hep/rules/bd0xx.py
inspire_dojson/hep/rules/bd1xx.py
inspire_dojson/hep/rules/bd2xx.py
inspire_dojson/hep/rules/bd3xx.py
inspire_dojson/hep/rules/bd4xx.py
inspire_dojson/hep/rules/bd5xx.py
inspire_dojson/hep/rules/bd6xx.py
inspire_dojson/hep/rules/bd7xx.py
inspire_dojson/hep/rules/bd9xx.py
inspire_dojson/hep/rules/bdFFT.py
inspire_dojson/hepnames/__init__.py
inspire_dojson/hepnames/model.py
inspire_dojson/hepnames/rules.py
inspire_dojson/institutions/__init__.py
inspire_dojson/institutions/model.py
inspire_dojson/institutions/rules.py
inspire_dojson/journals/__init__.py
inspire_dojson/journals/model.py
inspire_dojson/journals/rules.py
inspire_dojson/utils/__init__.py
inspire_dojson/utils/geo.py
inspire_dojson-63.2.32.dist-info/LICENSE
inspire_dojson-63.2.32.dist-info/METADATA
inspire_dojson-63.2.32.dist-info/WHEEL
inspire_dojson-63.2.32.dist-info/top_level.txt
inspire_dojson-63.2.32.dist-info/RECORD
