Metadata-Version: 2.1
Name: inspire-dojson
Version: 63.2.32
Summary: INSPIRE-specific rules to transform from MARCXML to JSON and back.
Home-page: https://github.com/inspirehep/inspire-dojson
Author: CERN
Author-email: admin@inspirehep.net
License: GPLv3
Platform: any
Classifier: Development Status :: 4 - Beta
Classifier: Environment :: Web Environment
Classifier: Intended Audience :: Developers
Classifier: License :: OSI Approved :: GNU General Public License v3 (GPLv3)
Classifier: Operating System :: OS Independent
Classifier: Programming Language :: Python
Classifier: Programming Language :: Python :: 3
Classifier: Programming Language :: Python :: 3.11
Classifier: Topic :: Internet :: WWW/HTTP :: Dynamic Content
Classifier: Topic :: Software Development :: Libraries :: Python Modules
License-File: LICENSE
Requires-Dist: Flask>=0.12.3
Requires-Dist: IDUtils>=1.0.1,~=1.0
Requires-Dist: dojson>=1.3.1,~=1.0
Requires-Dist: inspire-schemas
Requires-Dist: inspire-utils>=3.0.65,~=3.0
Requires-Dist: langdetect>=1.0.7,~=1.0
Requires-Dist: pycountry>=17.5.4,~=17.0
Requires-Dist: MarkupSafe>=1.1.1
Requires-Dist: urllib3~=1.25.0
Provides-Extra: all
Requires-Dist: flake8-future-import>=0.4.3,~=0.0; extra == "all"
Requires-Dist: mock>=2.0.0,~=2.0; extra == "all"
Requires-Dist: pytest-cov>=2.6.1,~=2.0; extra == "all"
Requires-Dist: pre-commit==3.5.0; extra == "all"
Requires-Dist: pytest>=4.6,~=4.0; python_version == "2.7" and extra == "all"
Requires-Dist: pytest>=6.2.5,~=6.0; python_version >= "3" and extra == "all"
Provides-Extra: dev
Requires-Dist: pre-commit==3.5.0; extra == "dev"
Provides-Extra: docs
Provides-Extra: tests
Requires-Dist: flake8-future-import>=0.4.3,~=0.0; extra == "tests"
Requires-Dist: mock>=2.0.0,~=2.0; extra == "tests"
Requires-Dist: pytest-cov>=2.6.1,~=2.0; extra == "tests"
Requires-Dist: pytest>=4.6,~=4.0; python_version == "2.7" and extra == "tests"
Requires-Dist: pytest>=6.2.5,~=6.0; python_version >= "3" and extra == "tests"
